[{"id":1,"imagename":"AfterSun.png","uploadeddate":"2023-02-04T09:17:31.656Z","rating":7},{"id":2,"imagename":"Happening.jpg","uploadeddate":"2023-02-04T09:17:31.656Z","rating":7},{"id":3,"imagename":"K.G.F.-Chapter.jpg","uploadeddate":"2023-02-04T09:17:31.656Z","rating":5.5},{"id":4,"imagename":"Living.jpg","uploadeddate":"2023-02-04T09:17:31.656Z","rating":9},{"id":5,"imagename":"Prey.jpg","uploadeddate":"2023-02-04T09:17:31.656Z","rating":4},{"id":6,"imagename":"RRR.jpg","uploadeddate":"2023-02-04T09:17:31.656Z","rating":3.5},{"id":7,"imagename":"The Quiet Girl.jpg","uploadeddate":"2023-02-04T09:17:31.656Z","rating":4},{"id":8,"imagename":"The Women King.jpg","uploadeddate":"2023-02-04T09:17:31.656Z","rating":4.2},{"id":9,"imagename":"The worst Person in the World.jpg","uploadeddate":"2023-02-04T09:17:31.656Z","rating":3.2},{"id":10,"imagename":"The_banshees_of_inisherin_Quad.jpg","uploadeddate":"2023-02-04T09:17:31.656Z","rating":8.5},{"id":11,"imagename":"The-northman.jpg","uploadeddate":"2023-02-04T09:17:31.656Z","rating":3.2},{"id":12,"imagename":"LionKutty.jpg","uploadeddate":"2023-02-04T09:17:31.656Z","rating":3.5},{"id":13,"imagename":"Top-Gun.jpg","uploadeddate":"2023-02-04T09:17:31.656Z","rating":7.75},{"id":14,"imagename":"Vikram.jpg","uploadeddate":"2023-02-04T09:17:31.656Z","rating":7.5},{"id":15,"imagename":"avatar2.jpg","uploadeddate":"2023-02-04T09:17:31.656Z","rating":9}]